CHANGES.txt
LICENSE.txt
MANIFEST.in
README.txt
TODO.txt
buildout.cfg
setup.py
test-plone-3.3.x.cfg
test-plone-4.0.x.cfg
Products/__init__.py
Products/__init__.pyc
Products.takeaction.egg-info/PKG-INFO
Products.takeaction.egg-info/SOURCES.txt
Products.takeaction.egg-info/dependency_links.txt
Products.takeaction.egg-info/entry_points.txt
Products.takeaction.egg-info/namespace_packages.txt
Products.takeaction.egg-info/not-zip-safe
Products.takeaction.egg-info/requires.txt
Products.takeaction.egg-info/top_level.txt
Products/takeaction/__init__.py
Products/takeaction/configure.zcml
Products/takeaction/exportimport.py
Products/takeaction/interfaces.py
Products/takeaction/patches.py
Products/takeaction/takeaction.py
Products/takeaction/tool.gif
Products/takeaction/version.txt
Products/takeaction/browser/__init__.py
Products/takeaction/browser/configure.zcml
Products/takeaction/browser/takeaction.pt
Products/takeaction/browser/takeaction.py
Products/takeaction/profiles/default/actions.xml
Products/takeaction/profiles/default/export_steps.xml
Products/takeaction/profiles/default/import_steps.xml
Products/takeaction/profiles/default/takeaction.xml
Products/takeaction/profiles/default/toolset.xml
Products/takeaction/tests/__init__.py
Products/takeaction/tests/test_exportimport.py
Products/takeaction/tests/test_takeaction.py