Metadata-Version: 1.0
Name: Products.takeaction
Version: 1.0
Summary: takeaction, content as actions
Home-page: http://plone.org/products/takeaction
Author: Jarn
Author-email: info@jarn.com
License: GPL
Keywords: content actions translatable
Platform: UNKNOWN
Classifier: Framework :: Plone
Classifier: Framework :: Zope2
Classifier: Programming Language :: Python
Classifier: Topic :: Software Development :: Libraries :: Python Modules
